odoo/addons/ssi_partner_portal/README.rst
odoo/addons/ssi_partner_portal/__init__.py
odoo/addons/ssi_partner_portal/__manifest__.py
odoo/addons/ssi_partner_portal/controllers/__init__.py
odoo/addons/ssi_partner_portal/controllers/portal.py
odoo/addons/ssi_partner_portal/models/__init__.py
odoo/addons/ssi_partner_portal/models/portal_partner_bank_account.py
odoo/addons/ssi_partner_portal/security/ir.model.access.csv
odoo/addons/ssi_partner_portal/security/ir_rule_data.xml
odoo/addons/ssi_partner_portal/static/description/icon.png
odoo/addons/ssi_partner_portal/static/src/css/bootstrap.css
odoo/addons/ssi_partner_portal/static/src/scss/portal.scss
odoo/addons/ssi_partner_portal/views/assets.xml
odoo/addons/ssi_partner_portal/views/portal_templates.xml
odoo14_addon_ssi_partner_portal-14.0.1.2.0.dist-info/METADATA
odoo14_addon_ssi_partner_portal-14.0.1.2.0.dist-info/WHEEL
odoo14_addon_ssi_partner_portal-14.0.1.2.0.dist-info/top_level.txt
odoo14_addon_ssi_partner_portal-14.0.1.2.0.dist-info/RECORD
